itk/GrowCutPython.py
itk/_GrowCutPython.pyd
itk/__init_growcut__.py
itk/itkFastGrowCutPython.py
itk/Configuration/GrowCutConfig.py
itk/Configuration/GrowCut_snake_case.py
itk_growcut-1.0.1.dist-info/licenses/LICENSE
itk_growcut.libs/.load-order-itk_growcut-1.0.1
itk_growcut.libs/msvcp140.dll
itk_growcut.libs/tbb12.dll
itk_growcut-1.0.1.dist-info/DELVEWHEEL
itk_growcut-1.0.1.dist-info/METADATA
itk_growcut-1.0.1.dist-info/WHEEL
itk_growcut-1.0.1.dist-info/RECORD
