Metadata-Version: 2.1
Name: itk-growcut
Version: 1.0.1
Summary: Segments a 3D image from foreground and background seeds.
Keywords: itk,InsightToolkit
Author-Email: Insight Software Consortium <itk+community@discourse.itk.org>
License:                                  Apache License
Classifier: Development Status :: 4 - Beta
Classifier: Intended Audience :: Developers
Classifier: Intended Audience :: Education
Classifier: Intended Audience :: Healthcare Industry
Classifier: Intended Audience :: Science/Research
Classifier: License :: OSI Approved :: Apache Software License
Classifier: Operating System :: Android
Classifier: Operating System :: MacOS
Classifier: Operating System :: Microsoft :: Windows
Classifier: Operating System :: POSIX
Classifier: Operating System :: Unix
Classifier: Programming Language :: C++
Classifier: Programming Language :: Python
Classifier: Topic :: Scientific/Engineering
Classifier: Topic :: Scientific/Engineering :: Information Analysis
Classifier: Topic :: Scientific/Engineering :: Medical Science Apps.
Classifier: Topic :: Software Development :: Libraries
Project-URL: Download, https://github.com/InsightSoftwareConsortium/ITKGrowCut
Project-URL: Homepage, https://github.com/InsightSoftwareConsortium/ITKGrowCut
Requires-Python: >=3.9
Requires-Dist: itk==5.4.*
